__init__.py
ax_devil_mqtt/__init__.py
ax_devil_mqtt/core/manager.py
ax_devil_mqtt/core/recorder.py
ax_devil_mqtt/core/replay.py
ax_devil_mqtt/core/subscriber.py
ax_devil_mqtt/core/temporary_analytics_mqtt_publisher.py
ax_devil_mqtt/core/types.py
ax_devil_mqtt/examples/cli.py
ax_devil_mqtt-0.3.0.dist-info/licenses/LICENSE
ax_devil_mqtt-0.3.0.dist-info/METADATA
ax_devil_mqtt-0.3.0.dist-info/WHEEL
ax_devil_mqtt-0.3.0.dist-info/entry_points.txt
ax_devil_mqtt-0.3.0.dist-info/top_level.txt
ax_devil_mqtt-0.3.0.dist-info/RECORD
