Metadata-Version: 2.4
Name: ax-devil-mqtt
Version: 0.3.0
Summary: Python package for setting up and retrieving data from Axis devices using MQTT
Author-email: Rasmus Rynell <Rynell.Rasmus@gmail.com>
License: MIT
Project-URL: Homepage, https://github.com/rasmusrynell/ax-devil-mqtt
Project-URL: Repository, https://github.com/rasmusrynell/ax-devil-mqtt.git
Project-URL: Documentation, https://github.com/rasmusrynell/ax-devil-mqtt#readme
Project-URL: Bug Tracker, https://github.com/rasmusrynell/ax-devil-mqtt/issues
Keywords: axis,mqtt,camera,analytics,iot
Classifier: Development Status :: 3 - Alpha
Classifier: Intended Audience :: Developers
Classifier: License :: OSI Approved :: MIT License
Classifier: Programming Language :: Python :: 3.10
Classifier: Programming Language :: Python :: 3.11
Classifier: Topic :: Software Development :: Libraries :: Python Modules
Classifier: Topic :: System :: Networking :: Monitoring
Requires-Python: >=3.10
License-File: LICENSE
Requires-Dist: ax-devil-device-api>=0.3.2
Requires-Dist: paho-mqtt>=1.6.1
Requires-Dist: python-dateutil>=2.8.2
Requires-Dist: click>=8.0.0
Dynamic: license-file
